{
    "products": [
        {
            "id": 1,
            "name": "Elegant Evening Gown",
            "description": "A stunning floor-length gown perfect for formal events and galas.",
            "price": 599.99,
            "originalPrice": 599.99,
            "image": "/images/elegant-evening-gown.jpg",
            "category": "women",
            "subcategory": "dresses",
            "brand": "Luxe Couture",
            "colors": ["Black", "Navy", "Burgundy"],
            "sizes": ["XS", "S", "M", "L", "XL"],
            "inStock": true,
            "rating": 4.8,
            "featured": true
        },
        {
            "id": 2,
            "name": "Classic Tailored Suit",
            "description": "A sophisticated suit crafted from premium Italian wool for the modern gentleman.",
            "price": 899.99,
            "originalPrice": 999.99,
            "image": "/images/classic-tailored-suit.jpg",
            "category": "men",
            "subcategory": "suits",
            "brand": "Savile Row",
            "colors": ["Charcoal", "Navy", "Black"],
            "sizes": ["38R", "40R", "42R", "44R", "46R"],
            "inStock": true,
            "rating": 4.9,
            "featured": true
        },
        {
            "id": 3,
            "name": "Designer Kids Party Dress",
            "description": "An adorable party dress for little ones, perfect for special occasions.",
            "price": 129.99,
            "originalPrice": 149.99,
            "image": "/images/kids-party-dress.jpg",
            "category": "kids",
            "subcategory": "dresses",
            "brand": "Little Luxuries",
            "colors": ["Pink", "White", "Lavender"],
            "sizes": ["2T", "3T", "4T", "5", "6"],
            "inStock": true,
            "rating": 4.7,
            "featured": true
        },
        {
            "id": 4,
            "name": "Luxury Leather Handbag",
            "description": "A spacious and stylish handbag crafted from premium Italian leather.",
            "price": 799.99,
            "originalPrice": 899.99,
            "image": "/images/leather-handbag.jpg",
            "category": "women",
            "subcategory": "accessories",
            "brand": "Milano Leather",
            "colors": ["Black", "Brown", "Tan"],
            "sizes": ["One Size"],
            "inStock": true,
            "rating": 4.8,
            "featured": true
        },
        {
            "id": 5,
            "name": "Cashmere Sweater",
            "description": "A luxuriously soft cashmere sweater for ultimate comfort and style.",
            "price": 349.99,
            "originalPrice": 399.99,
            "image": "/images/cashmere-sweater.jpg",
            "category": "unisex",
            "subcategory": "knitwear",
            "brand": "Soft Luxe",
            "colors": ["Cream", "Gray", "Black", "Navy"],
            "sizes": ["S", "M", "L", "XL"],
            "inStock": true,
            "rating": 4.7,
            "featured": true
        },
        {
            "id": 6,
            "name": "Silk Scarf",
            "description": "A luxurious silk scarf with a beautiful print.",
            "price": 129.99,
            "originalPrice": 149.99,
            "image": "/images/silk-scarf.jpg",
            "category": "accessories",
            "subcategory": "scarves",
            "brand": "Luxe Accessories",
            "colors": ["Multicolor"],
            "sizes": ["One Size"],
            "inStock": true,
            "rating": 4.6,
            "featured": false
        },
        {
            "id": 7,
            "name": "Leather Oxford Shoes",
            "description": "Classic leather Oxford shoes for a timeless look.",
            "price": 299.99,
            "originalPrice": 349.99,
            "image": "/images/leather-oxford-shoes.jpg",
            "category": "men",
            "subcategory": "shoes",
            "brand": "Classic Footwear",
            "colors": ["Black", "Brown"],
            "sizes": ["7", "8", "9", "10", "11", "12"],
            "inStock": true,
            "rating": 4.8,
            "featured": false
        },
        {
            "id": 8,
            "name": "Diamond Tennis Bracelet",
            "description": "An elegant diamond tennis bracelet for a touch of luxury.",
            "price": 3999.99,
            "originalPrice": 4499.99,
            "image": "/images/diamond-tennis-bracelet.jpg",
            "category": "women",
            "subcategory": "jewelry",
            "brand": "Brilliant Gems",
            "colors": ["White Gold", "Yellow Gold"],
            "sizes": ["6.5 inch", "7 inch", "7.5 inch"],
            "inStock": true,
            "rating": 4.9,
            "featured": true
        },
        {
            "id": 9,
            "name": "Designer Sunglasses",
            "description": "Stylish designer sunglasses with UV protection.",
            "price": 249.99,
            "originalPrice": 299.99,
            "image": "/images/designer-sunglasses.jpg",
            "category": "accessories",
            "subcategory": "eyewear",
            "brand": "Luxe Shades",
            "colors": ["Black", "Tortoiseshell", "Gold"],
            "sizes": ["One Size"],
            "inStock": true,
            "rating": 4.7,
            "featured": false
        },
        {
            "id": 10,
            "name": "Men's Leather Jacket",
            "description": "A classic leather jacket for the modern man.",
            "price": 499.99,
            "originalPrice": 599.99,
            "image": "/images/mens-leather-jacket.jpg",
            "category": "men",
            "subcategory": "outerwear",
            "brand": "Urban Edge",
            "colors": ["Black", "Brown"],
            "sizes": ["S", "M", "L", "XL", "XXL"],
            "inStock": true,
            "rating": 4.8,
            "featured": false
        },
        {
            "id": 11,
            "name": "Women's Trench Coat",
            "description": "A timeless trench coat for sophisticated style.",
            "price": 399.99,
            "originalPrice": 449.99,
            "image": "/images/womens-trench-coat.jpg",
            "category": "women",
            "subcategory": "outerwear",
            "brand": "Chic Essentials",
            "colors": ["Beige", "Black", "Navy"],
            "sizes": ["XS", "S", "M", "L", "XL"],
            "inStock": true,
            "rating": 4.7,
            "featured": false
        },
        {
            "id": 12,
            "name": "Kids' Sneakers",
            "description": "Comfortable and stylish sneakers for active kids.",
            "price": 79.99,
            "originalPrice": 89.99,
            "image": "/images/kids-sneakers.jpg",
            "category": "kids",
            "subcategory": "shoes",
            "brand": "Little Steps",
            "colors": ["Blue", "Pink", "Green"],
            "sizes": ["1", "2", "3", "4", "5"],
            "inStock": true,
            "rating": 4.6,
            "featured": false
        },
        {
            "id": 13,
            "name": "Luxury Watch",
            "description": "A premium timepiece combining style and precision.",
            "price": 2999.99,
            "originalPrice": 3299.99,
            "image": "/images/luxury-watch.jpg",
            "category": "accessories",
            "subcategory": "watches",
            "brand": "Timeless Elegance",
            "colors": ["Silver", "Gold", "Rose Gold"],
            "sizes": ["One Size"],
            "inStock": true,
            "rating": 4.9,
            "featured": true
        },
        {
            "id": 14,
            "name": "Silk Blouse",
            "description": "An elegant silk blouse for a sophisticated look.",
            "price": 199.99,
            "originalPrice": 229.99,
            "image": "/images/silk-blouse.jpg",
            "category": "women",
            "subcategory": "tops",
            "brand": "Luxe Couture",
            "colors": ["White", "Cream", "Black"],
            "sizes": ["XS", "S", "M", "L", "XL"],
            "inStock": true,
            "rating": 4.7,
            "featured": false
        },
        {
            "id": 15,
            "name": "Men's Dress Shirt",
            "description": "A crisp, tailored dress shirt for formal occasions.",
            "price": 89.99,
            "originalPrice": 99.99,
            "image": "/images/mens-dress-shirt.jpg",
            "category": "men",
            "subcategory": "shirts",
            "brand": "Savile Row",
            "colors": ["White", "Light Blue", "Pink"],
            "sizes": ["15", "15.5", "16", "16.5", "17"],
            "inStock": true,
            "rating": 4.6,
            "featured": false
        },
        {
            "id": 16,
            "name": "Kids' Winter Coat",
            "description": "A warm and stylish winter coat for children.",
            "price": 149.99,
            "originalPrice": 179.99,
            "image": "/images/kids-winter-coat.jpg",
            "category": "kids",
            "subcategory": "outerwear",
            "brand": "Little Luxuries",
            "colors": ["Red", "Navy", "Purple"],
            "sizes": ["4", "5", "6", "7", "8"],
            "inStock": true,
            "rating": 4.8,
            "featured": false
        },
        {
            "id": 17,
            "name": "Designer Clutch",
            "description": "An elegant clutch for evening events.",
            "price": 299.99,
            "originalPrice": 349.99,
            "image": "/images/designer-clutch.jpg",
            "category": "women",
            "subcategory": "accessories",
            "brand": "Milano Leather",
            "colors": ["Black", "Gold", "Silver"],
            "sizes": ["One Size"],
            "inStock": true,
            "rating": 4.7,
            "featured": false
        },
        {
            "id": 18,
            "name": "Men's Cufflinks",
            "description": "Elegant cufflinks to complement formal attire.",
            "price": 129.99,
            "originalPrice": 149.99,
            "image": "/images/mens-cufflinks.jpg",
            "category": "men",
            "subcategory": "accessories",
            "brand": "Luxe Accessories",
            "colors": ["Silver", "Gold"],
            "sizes": ["One Size"],
            "inStock": true,
            "rating": 4.6,
            "featured": false
        },
        {
            "id": 19,
            "name": "Girls' Ballet Flats",
            "description": "Comfortable and stylish ballet flats for young girls.",
            "price": 59.99,
            "originalPrice": 69.99,
            "image": "/images/girls-ballet-flats.jpg",
            "category": "kids",
            "subcategory": "shoes",
            "brand": "Little Steps",
            "colors": ["Pink", "Black", "White"],
            "sizes": ["10", "11", "12", "13", "1"],
            "inStock": true,
            "rating": 4.5,
            "featured": false
        },
        {
            "id": 20,
            "name": "Luxury Perfume Set",
            "description": "A set of premium fragrances for the discerning individual.",
            "price": 399.99,
            "originalPrice": 449.99,
            "image": "/images/luxury-perfume-set.jpg",
            "category": "accessories",
            "subcategory": "fragrances",
            "brand": "Essence of Luxury",
            "colors": ["N/A"],
            "sizes": ["50ml", "100ml"],
            "inStock": true,
            "rating": 4.9,
            "featured": true
        }
    ],
    "featuredProducts": [
        {
            "id": 1,
            "name": "Elegant Evening Gown",
            "image": "/images/elegant-evening-gown.jpg",
            "price": 599.99
        },
        {
            "id": 2,
            "name": "Classic Tailored Suit",
            "image": "/images/classic-tailored-suit.jpg",
            "price": 899.99
        },
        {
            "id": 3,
            "name": "Designer Kids Party Dress",
            "image": "/images/kids-party-dress.jpg",
            "price": 129.99
        },
        {
            "id": 4,
            "name": "Luxury Leather Handbag",
            "image": "/images/leather-handbag.jpg",
            "price": 799.99
        },
        {
            "id": 5,
            "name": "Cashmere Sweater",
            "image": "/images/cashmere-sweater.jpg",
            "price": 349.99
        },
        {
            "id": 8,
            "name": "Diamond Tennis Bracelet",
            "image": "/images/diamond-tennis-bracelet.jpg",
            "price": 3999.99
        },
        {
            "id": 13,
            "name": "Luxury Watch",
            "image": "/images/luxury-watch.jpg",
            "price": 2999.99
        },
        {
            "id": 20,
            "name": "Luxury Perfume Set",
            "image": "/images/luxury-perfume-set.jpg",
            "price": 399.99
        }
    ]
}
